{
  "_class": "shapeGroup",
  "clippingMaskMode": 0,
  "do_objectID": "C48B8153-6931-46F5-8FAA-E956F107A637",
  "exportOptions": {
    "_class": "exportOptions",
    "exportFormats": [
    ],
    "includedLayerIds": [
    ],
    "layerOptions": 0,
    "shouldTrim": false
  },
  "frame": {
    "_class": "rect",
    "constrainProportions": false,
    "height": 14.60438180759505,
    "width": 8.324479290028025,
    "x": 94.370444502174,
    "y": 20.07409061352785
  },
  "hasClickThrough": false,
  "hasClippingMask": false,
  "isFlippedHorizontal": false,
  "isFlippedVertical": false,
  "isLocked": false,
  "isVisible": true,
  "layerListExpandedType": 1,
  "layers": [
    {
      "class": "shapePath",
      "id": "8072766C-8B5D-4100-879B-99671F8D117B"
    }
  ],
  "name": "hirarchical-separator",
  "nameIsFixed": true,
  "resizingConstraint": 63,
  "resizingType": 0,
  "rotation": 0,
  "shouldBreakMaskChain": false,
  "style": {
    "_class": "style",
    "endDecorationType": 0,
    "fills": [
      {
        "_class": "fill",
        "color": {
          "_class": "color",
          "alpha": 1,
          "blue": 0.5828321794132297,
          "green": 0.5765829265203655,
          "red": 0.6140784438775511
        },
        "fillType": 0,
        "isEnabled": true,
        "noiseIndex": 0,
        "noiseIntensity": 0,
        "patternFillType": 1,
        "patternTileScale": 1
      }
    ],
    "miterLimit": 10,
    "startDecorationType": 0
  },
  "windingRule": 1
}