{
  "_class": "bitmap",
  "clippingMask": "{{0, 0}, {1, 1}}",
  "do_objectID": "02396E91-9F7A-44E7-B2F6-D2871CAF1126",
  "exportOptions": {
    "_class": "exportOptions",
    "exportFormats": [
    ],
    "includedLayerIds": [
    ],
    "layerOptions": 0,
    "shouldTrim": false
  },
  "fillReplacesImage": false,
  "frame": {
    "_class": "rect",
    "constrainProportions": true,
    "height": 428.2545872696556,
    "width": 642.3818809044834,
    "x": -147.159688420959,
    "y": -0.4464589473060237
  },
  "image": {
    "_class": "MSJSONFileReference",
    "_ref": "images/e65206e5454606f1bda4cf293ef9f1a849ff7467",
    "_ref_class": "MSImageData"
  },
  "isFlippedHorizontal": false,
  "isFlippedVertical": false,
  "isLocked": false,
  "isVisible": true,
  "layerListExpandedType": 0,
  "name": "andre-benz-230808",
  "nameIsFixed": false,
  "nineSliceCenterRect": "{{0, 0}, {0, 0}}",
  "nineSliceScale": "{0, 0}",
  "resizingConstraint": 63,
  "resizingType": 0,
  "rotation": 0,
  "shouldBreakMaskChain": false,
  "style": {
    "_class": "style",
    "blur": {
      "_class": "blur",
      "center": "{0.5, 0.5}",
      "isEnabled": false,
      "motionAngle": 0,
      "radius": 11.4,
      "type": 0
    },
    "endDecorationType": 0,
    "miterLimit": 10,
    "startDecorationType": 0
  }
}